{
  "format_version": "1.13.0",
  "minecraft:feature_rules": {
    "description": {
      "identifier": "niaserver:world_air_top_feature",
      "places_feature": "niaserver:air_top_feature"
    },
    "conditions": {
      "placement_pass": "after_sky_pass",
      "minecraft:biome_filter": [
        {
          "any_of": [
            {
              "test": "has_biome_tag",
              "operator": "==",
              "value": "overworld"
            },
            {
              "test": "has_biome_tag",
              "operator": "==",
              "value": "overworld_generation"
            }
          ]
        }
      ]
    },
    "distribution": {
      "iterations": 32,
      "coordinate_eval_order": "zyx",
      "x": {
        "distribution": "uniform",
        "extent": [
          0,
          16
        ]
      },
      "y": {
        "distribution": "uniform",
        "extent": [
          112,
          150
        ]
      },
      "z": {
        "distribution": "uniform",
        "extent": [
          0,
          16
        ]
      }
    }
  }
}